SeTeEscapoLaTortuga/Turtle.py
SeTeEscapoLaTortuga/__init__.py
SeTeEscapoLaTortuga-0.1.dist-info/LICENSE
SeTeEscapoLaTortuga-0.1.dist-info/METADATA
SeTeEscapoLaTortuga-0.1.dist-info/WHEEL
SeTeEscapoLaTortuga-0.1.dist-info/top_level.txt
SeTeEscapoLaTortuga-0.1.dist-info/RECORD
