Metadata-Version: 2.1
Name: SeTeEscapoLaTortuga
Version: 0.1
Summary: A spanish translation of ColabTurtle from Tolga Atam: https://github.com/tolgaatam/ColabTurtle
Home-page: https://github.com/amiune/SeTeEscapoLaTortuga
Author: Hernan Amiune
Author-email: amiune@gmail.com
License: MIT
License-File: LICENSE
